spikelib/__init__.py
spikelib/fitting.py
spikelib/io.py
spikelib/models.py
spikelib/preprocessing.py
spikelib/spiketools.py
spikelib/stimtools.py
spikelib/utils.py
spikelib/visualizations.py
spikelib-0.1.1.dist-info/DESCRIPTION.rst
spikelib-0.1.1.dist-info/METADATA
spikelib-0.1.1.dist-info/RECORD
spikelib-0.1.1.dist-info/WHEEL
spikelib-0.1.1.dist-info/metadata.json
spikelib-0.1.1.dist-info/top_level.txt
