Metadata-Version: 2.0
Name: spikelib
Version: 0.1.1
Summary: Set of tools to analyze neuronal activity from spiketimes
Home-page: https://github.com/creyesp/spikelib
Author: Cesar Reyes
Author-email: cesar.reyesp@gmail.com
License: UNKNOWN
Platform: UNKNOWN
Classifier: Intended Audience :: Science/Research
Classifier: Topic :: Scientific/Engineering :: Information Analysis
Classifier: Topic :: Scientific/Engineering :: Visualization
Classifier: License :: OSI Approved :: MIT License
Classifier: Operating System :: OS Independent
Classifier: Programming Language :: Python :: 3
Classifier: Programming Language :: Python :: 2.7
Requires-Dist: numpy (>=1.15.4)
Requires-Dist: scipy (>=1.1.0)
Requires-Dist: matplotlib (>=2.2.3)
Requires-Dist: scikit-learn (>=0.20.1)
Requires-Dist: peakutils (>=1.3.0)
Requires-Dist: pandas (>=0.23.4)
Requires-Dist: h5py (>=2.8.0)
Requires-Dist: lmfit (>=0.9.12)
